job_analyzer_support.py
read_log_messages.py
read_zd_tickets.py
mcp_support-0.1.0.dist-info/METADATA
mcp_support-0.1.0.dist-info/WHEEL
mcp_support-0.1.0.dist-info/entry_points.txt
mcp_support-0.1.0.dist-info/RECORD
