Metadata-Version: 2.4
Name: mcp-support
Version: 0.1.0
Summary: MCP Server for Job Analysis and Support - CloudWatch logs and Zendesk integration
Project-URL: Homepage, https://github.com/simetrik/job-analyzer-support
Project-URL: Repository, https://github.com/simetrik/job-analyzer-support
Project-URL: Issues, https://github.com/simetrik/job-analyzer-support/issues
Author-email: Simetrik Team <dev@simetrik.com>
License: MIT
Keywords: cloudwatch,job-analyzer,mcp,simetrik,support,zendesk
Classifier: Development Status :: 3 - Alpha
Classifier: Intended Audience :: Developers
Classifier: License :: OSI Approved :: MIT License
Classifier: Programming Language :: Python :: 3
Classifier: Programming Language :: Python :: 3.10
Classifier: Programming Language :: Python :: 3.11
Classifier: Programming Language :: Python :: 3.12
Classifier: Programming Language :: Python :: 3.13
Classifier: Topic :: Software Development :: Libraries :: Python Modules
Classifier: Topic :: System :: Monitoring
Requires-Python: >=3.10
Requires-Dist: boto3>=1.35.0
Requires-Dist: httpx>=0.28.1
Requires-Dist: mcp[cli]>=1.9.3
Requires-Dist: openpyxl>=3.1.2
Requires-Dist: pandas>=2.1.0
Requires-Dist: requests>=2.31.0
